uenginecli/__init__.py
uenginecli/client.py
uenginecli-1.0.5.dist-info/METADATA
uenginecli-1.0.5.dist-info/RECORD
uenginecli-1.0.5.dist-info/WHEEL
uenginecli-1.0.5.dist-info/top_level.txt
