Metadata-Version: 2.1
Name: uenginecli
Version: 1.0.5
Summary: a helper client library for accessing uengine-based APIs
Home-page: https://github.com/viert/uenginecli
Author: Pavel Vorobyov
Author-email: aquavitale@yandex.ru
License: MIT
Platform: UNKNOWN
Requires-Dist: requests
